nonebot_plugin_calc24/__init__.py
nonebot_plugin_calc24/calc24-data.json
nonebot_plugin_calc24/file_handle.py
nonebot_plugin_calc24/xj_calc24.py
nonebot_plugin_calc24-1.3.14.dist-info/LICENSE
nonebot_plugin_calc24-1.3.14.dist-info/METADATA
nonebot_plugin_calc24-1.3.14.dist-info/WHEEL
nonebot_plugin_calc24-1.3.14.dist-info/RECORD
