Metadata-Version: 2.1
Name: nonebot-plugin-calc24
Version: 1.3.14
Summary: A 24-point game plugin implemented using NoneBot.
Home-page: https://github.com/ajdgg/nonebot-plugin-calc24
License: LICENSE
Keywords: nonebot,nonebot2
Author: AwAjie
Author-email: 139576615+ajdgg@users.noreply.github.com
Requires-Python: >=3.8,<4.0
Classifier: License :: Other/Proprietary License
Classifier: Programming Language :: Python :: 3
Classifier: Programming Language :: Python :: 3.8
Classifier: Programming Language :: Python :: 3.9
Classifier: Programming Language :: Python :: 3.10
Classifier: Programming Language :: Python :: 3.11
Classifier: Programming Language :: Python :: 3.12
Requires-Dist: nonebot-adapter-onebot (>=2.0.0-beta.1,<3.0.0)
Requires-Dist: nonebot2 (>=2.2.0,<3.0.0)
Project-URL: Documentation, https://github.com/ajdgg/nonebot-plugin-calc24
Project-URL: Repository, https://github.com/ajdgg/nonebot-plugin-calc24
